README.md
sbmising.py
setup.py
sbmising.egg-info/PKG-INFO
sbmising.egg-info/SOURCES.txt
sbmising.egg-info/dependency_links.txt
sbmising.egg-info/requires.txt
sbmising.egg-info/top_level.txt