Metadata-Version: 2.1
Name: sbmising
Version: 0.1
Summary: simulated annealing for the recovery of symmetric stochastic block model
Home-page: https://github.com/zhaofeng-shu33/sbmising
Author: zhaofeng-shu33
Author-email: 616545598@qq.com
Maintainer: zhaofeng-shu33
Maintainer-email: 616545598@qq.com
License: Apache License Version 2.0
Platform: UNKNOWN
Classifier: Development Status :: 4 - Beta
Classifier: Programming Language :: Python :: 3.8
Classifier: Operating System :: OS Independent
